Workbook

Sheet Calculadora
A1: Calculadora de Precificação | RITO Sistemas
A2: Preencha principalmente as células amarelas. A planilha calcula pacote, cenários de preço e parcelamentos sugeridos automaticamente.
A4: Cliente | D4: Faixa mínima | E4: =IFERROR(INDEX(Parametros!$Q$5:$Q$11,MATCH($B$6,Parametros!$P$5:$P$11,0)),"")
A5: Projeto | D5: Faixa máxima | E5: =IFERROR(INDEX(Parametros!$R$5:$R$11,MATCH($B$6,Parametros!$P$5:$P$11,0)),"")
A6: Tipo de serviço | B6: Sistema sob medida de pequeno porte | D6: Status do ideal | E6: =IF(OR(E4="",E5=""),"Faixa aberta / usar hora técnica",IF($B$36<E4,"Abaixo da faixa de referência",IF($B$36>E5,"Acima da faixa de referência","Dentro da faixa de referência")))
A7: Pacote comercial | B7: Operacional | D7: Multiplicador do pacote | E7: =IFERROR(INDEX(Parametros!$U$5:$U$7,MATCH($B$7,Parametros!$T$5:$T$7,0)),1)
A8: Complexidade | B8: Média | D8: Descrição do pacote | E8: =IFERROR(INDEX(Parametros!$V$5:$V$7,MATCH($B$7,Parametros!$T$5:$T$7,0)),"")
A9: Urgência | B9: Normal | D9: Leitura do cenário | E9: =IFERROR(INDEX(Parametros!$AA$5:$AA$7,MATCH($B$14,Parametros!$X$5:$X$7,0)),"")
A10: Integrações | B10: Nenhuma | D10: Parcelamento sugerido | E10: =Parcelamento!$B$6
A11: Documentação extra | B11: Não
A12: Desconto (%) | B12: 0
A13: Custos de terceiros | B13: 0
A14: Cenário preferencial | B14: Ideal comercial
A17: Etapa | B17: Horas | C17: Valor/hora base | D17: Subtotal | E17: Observação
A18: Análise e descoberta | B18: 0 | C18: =IFERROR(INDEX(Parametros!$B$5:$B$11,MATCH(A18,Parametros!$A$5:$A$11,0)),0) | D18: =B18*C18
A19: Planejamento da solução | B19: 0 | C19: =IFERROR(INDEX(Parametros!$B$5:$B$11,MATCH(A19,Parametros!$A$5:$A$11,0)),0) | D19: =B19*C19
A20: Desenvolvimento | B20: 0 | C20: =IFERROR(INDEX(Parametros!$B$5:$B$11,MATCH(A20,Parametros!$A$5:$A$11,0)),0) | D20: =B20*C20
A21: Testes e ajustes | B21: 0 | C21: =IFERROR(INDEX(Parametros!$B$5:$B$11,MATCH(A21,Parametros!$A$5:$A$11,0)),0) | D21: =B21*C21
A22: Entrega e orientação | B22: 0 | C22: =IFERROR(INDEX(Parametros!$B$5:$B$11,MATCH(A22,Parametros!$A$5:$A$11,0)),0) | D22: =B22*C22
A23: Suporte inicial | B23: 0 | C23: =IFERROR(INDEX(Parametros!$B$5:$B$11,MATCH(A23,Parametros!$A$5:$A$11,0)),0) | D23: =B23*C23
A24: Treinamento adicional | B24: 0 | C24: =IFERROR(INDEX(Parametros!$B$5:$B$11,MATCH(A24,Parametros!$A$5:$A$11,0)),0) | D24: =B24*C24
A27: Horas totais | B27: =SUM(B18:B24) | D27: Como ler | E27: Use as horas por etapa como base. O pacote comercial ajusta a proposta ao posicionamento da oferta.
A28: Subtotal base | B28: =SUM(D18:D24) | D28: Pacotes | E28: Essencial reduz a proposta para algo mais enxuto; Operacional é a base padrão; Sob Medida protege escopo de maior personalização.
A29: Multiplicador de complexidade | B29: =IFERROR(INDEX(Parametros!$E$5:$E$7,MATCH($B$8,Parametros!$D$5:$D$7,0)),1) | D29: Cenários | E29: Mínimo = limite defensável, Ideal = referência principal, Premium = quando valor percebido, risco ou urgência forem maiores.
A30: Multiplicador de urgência | B30: =IFERROR(INDEX(Parametros!$H$5:$H$7,MATCH($B$9,Parametros!$G$5:$G$7,0)),1) | D30: Desconto | E30: Só aplicar desconto com justificativa comercial clara. Sempre preferir revisar escopo antes de baixar preço.
A31: Multiplicador de integrações | B31: =IFERROR(INDEX(Parametros!$K$5:$K$7,MATCH($B$10,Parametros!$J$5:$J$7,0)),1) | D31: Faixa de serviço | E31: Se o ideal ficar muito fora da faixa de referência, revisar escopo, pacote, risco ou tipo de serviço selecionado.
A32: Multiplicador de documentação | B32: =IFERROR(INDEX(Parametros!$N$5:$N$6,MATCH($B$11,Parametros!$M$5:$M$6,0)),1)
A33: Subtotal técnico ajustado | B33: =B28*B29*B30*B31*B32
A34: Base comercial do pacote | B34: =B33*IFERROR(INDEX(Parametros!$U$5:$U$7,MATCH($B$7,Parametros!$T$5:$T$7,0)),1)
A35: Mínimo defensável | B35: =Cenarios!H8
A36: Ideal comercial | B36: =Cenarios!H9
A37: Premium estratégico | B37: =Cenarios!H10
A38: Preço do cenário preferencial | B38: =IFERROR(INDEX(Cenarios!$H$8:$H$10,MATCH($B$14,Cenarios!$A$8:$A$10,0)),0)
A39: Valor/hora ideal | B39: =Cenarios!I9
A40: Modelo de parcelamento sugerido | B40: =Parcelamento!$B$6

Sheet Cenarios
A1: Comparação de Cenários e Pacotes
A2: Esta aba compara os cenários de preço para o pacote selecionado e mostra a diferença entre Essencial, Operacional e Sob Medida no cenário ideal.
A4: Projeto | B4: =Calculadora!B5 | D4: Pacote selecionado | E4: =Calculadora!B7
A5: Tipo de serviço | B5: =Calculadora!B6 | D5: Base comercial do pacote | E5: =Calculadora!B34
A7: Cenário | B7: Margem | C7: Mult. comercial | D7: Base do pacote | E7: Serviços antes do desconto | F7: Desconto | G7: Custos terceiros | H7: Total final | I7: Valor/hora | J7: Status vs faixa | K7: Uso sugerido
A8: =Parametros!X5 | B8: =Parametros!Y5 | C8: =Parametros!Z5 | D8: =Calculadora!$B$34 | E8: =(D8*C8)*(1+B8) | F8: =E8*Calculadora!$B$12 | G8: =Calculadora!$B$13 | H8: =E8-F8+G8 | I8: =IFERROR(H8/Calculadora!$B$27,0) | J8: =IF(OR(Calculadora!$E$4="",Calculadora!$E$5=""),"Faixa aberta / usar hora técnica",IF(H8<Calculadora!$E$4,"Abaixo da faixa",IF(H8>Calculadora!$E$5,"Acima da faixa","Dentro da faixa"))) | K8: =Parametros!AA5
A9: =Parametros!X6 | B9: =Parametros!Y6 | C9: =Parametros!Z6 | D9: =Calculadora!$B$34 | E9: =(D9*C9)*(1+B9) | F9: =E9*Calculadora!$B$12 | G9: =Calculadora!$B$13 | H9: =E9-F9+G9 | I9: =IFERROR(H9/Calculadora!$B$27,0) | J9: =IF(OR(Calculadora!$E$4="",Calculadora!$E$5=""),"Faixa aberta / usar hora técnica",IF(H9<Calculadora!$E$4,"Abaixo da faixa",IF(H9>Calculadora!$E$5,"Acima da faixa","Dentro da faixa"))) | K9: =Parametros!AA6
A10: =Parametros!X7 | B10: =Parametros!Y7 | C10: =Parametros!Z7 | D10: =Calculadora!$B$34 | E10: =(D10*C10)*(1+B10) | F10: =E10*Calculadora!$B$12 | G10: =Calculadora!$B$13 | H10: =E10-F10+G10 | I10: =IFERROR(H10/Calculadora!$B$27,0) | J10: =IF(OR(Calculadora!$E$4="",Calculadora!$E$5=""),"Faixa aberta / usar hora técnica",IF(H10<Calculadora!$E$4,"Abaixo da faixa",IF(H10>Calculadora!$E$5,"Acima da faixa","Dentro da faixa"))) | K10: =Parametros!AA7
A13: Pacote | B13: Multiplicador | C13: Total ideal | D13: Leitura
A14: =Parametros!T5 | B14: =Parametros!U5 | C14: =(((Calculadora!$B$33*B14)*INDEX(Parametros!$Z$5:$Z$7,MATCH("Ideal comercial",Parametros!$X$5:$X$7,0)))*(1+INDEX(Parametros!$Y$5:$Y$7,MATCH("Ideal comercial",Parametros!$X$5:$X$7,0))))-((((Calculadora!$B$33*B14)*INDEX(Parametros!$Z$5:$Z$7,MATCH("Ideal comercial",Parametros!$X$5:$X$7,0)))*(1+INDEX(Parametros!$Y$5:$Y$7,MATCH("Ideal comercial",Parametros!$X$5:$X$7,0))))*Calculadora!$B$12)+Calculadora!$B$13 | D14: =Parametros!V5
A15: =Parametros!T6 | B15: =Parametros!U6 | C15: =(((Calculadora!$B$33*B15)*INDEX(Parametros!$Z$5:$Z$7,MATCH("Ideal comercial",Parametros!$X$5:$X$7,0)))*(1+INDEX(Parametros!$Y$5:$Y$7,MATCH("Ideal comercial",Parametros!$X$5:$X$7,0))))-((((Calculadora!$B$33*B15)*INDEX(Parametros!$Z$5:$Z$7,MATCH("Ideal comercial",Parametros!$X$5:$X$7,0)))*(1+INDEX(Parametros!$Y$5:$Y$7,MATCH("Ideal comercial",Parametros!$X$5:$X$7,0))))*Calculadora!$B$12)+Calculadora!$B$13 | D15: =Parametros!V6
A16: =Parametros!T7 | B16: =Parametros!U7 | C16: =(((Calculadora!$B$33*B16)*INDEX(Parametros!$Z$5:$Z$7,MATCH("Ideal comercial",Parametros!$X$5:$X$7,0)))*(1+INDEX(Parametros!$Y$5:$Y$7,MATCH("Ideal comercial",Parametros!$X$5:$X$7,0))))-((((Calculadora!$B$33*B16)*INDEX(Parametros!$Z$5:$Z$7,MATCH("Ideal comercial",Parametros!$X$5:$X$7,0)))*(1+INDEX(Parametros!$Y$5:$Y$7,MATCH("Ideal comercial",Parametros!$X$5:$X$7,0))))*Calculadora!$B$12)+Calculadora!$B$13 | D16: =Parametros!V7

Sheet Parcelamento
A1: Simulação de Parcelamento por Marcos
A2: Escolha o cenário-base e compare os modelos de 2, 3 e 4 marcos. O total vem automaticamente da aba de cenários.
A4: Cenário-base | B4: =Calculadora!$B$14
A5: Total da proposta | B5: =IFERROR(INDEX(Cenarios!$H$8:$H$10,MATCH($B$4,Cenarios!$A$8:$A$10,0)),0)
A6: Modelo sugerido | B6: =IF(B5<=5000,"2 marcos",IF(B5<=15000,"3 marcos","4 marcos"))
A7: Valor/hora do cenário | B7: =IFERROR(INDEX(Cenarios!$I$8:$I$10,MATCH($B$4,Cenarios!$A$8:$A$10,0)),0)
A8: Status vs faixa | B8: =IFERROR(INDEX(Cenarios!$J$8:$J$10,MATCH($B$4,Cenarios!$A$8:$A$10,0)),"")
A10: Modelo 2 marcos | B10: % | C10: Valor | E10: Modelo 3 marcos | F10: % | G10: Valor | I10: Modelo 4 marcos | J10: % | K10: Valor
A11: Entrada | B11: =Parametros!$AD$5 | C11: =$B11*$B$5 | E11: Entrada | F11: =Parametros!$AD$6 | G11: =$F11*$B$5 | I11: Entrada | J11: =Parametros!$AD$7 | K11: =$J11*$B$5
A12: Entrega final | B12: =Parametros!$AE$5 | C12: =$B12*$B$5 | E12: Marco intermediário | F12: =Parametros!$AE$6 | G12: =$F12*$B$5 | I12: Planejamento aprovado | J12: =Parametros!$AE$7 | K12: =$J12*$B$5
A13: Total | B13: =SUM(B11:B12) | C13: =SUM(C11:C12) | E13: Entrega final | F13: =Parametros!$AF$6 | G13: =$F13*$B$5 | I13: Primeira entrega | J13: =Parametros!$AF$7 | K13: =$J13*$B$5
E14: Total | F14: =SUM(F11:F13) | G14: =SUM(G11:G13) | I14: Entrega final | J14: =Parametros!$AG$7 | K14: =$J14*$B$5
I15: Total | J15: =SUM(J11:J14) | K15: =SUM(K11:K14)
A18: Leitura | B18: 2 marcos funciona melhor para propostas menores. 3 marcos é a estrutura padrão mais equilibrada. 4 marcos ajuda a proteger caixa e risco em projetos maiores.

Sheet Resumo-Proposta
A1: Resumo de Orçamento e Proposta
A2: Esta aba foi desenhada para revisão rápida e exportação em PDF direto pelo Excel.
A4: Cliente | B4: =Calculadora!B4 | D4: Prazo estimado
A5: Projeto | B5: =Calculadora!B5 | D5: Validade da proposta
A6: Tipo de serviço | B6: =Calculadora!B6 | D6: Data de emissão | E6: =TODAY()
A7: Pacote comercial | B7: =Calculadora!B7 | D7: Modelo de parcelamento | E7: =Parcelamento!B6
A8: Cenário adotado | B8: =Calculadora!B14 | D8: Parcela 1 | E8: =IF(E7="2 marcos",Parcelamento!C11,IF(E7="3 marcos",Parcelamento!G11,Parcelamento!K11))
A9: Investimento sugerido | B9: =Calculadora!B38 | D9: Parcela 2 | E9: =IF(E7="2 marcos",Parcelamento!C12,IF(E7="3 marcos",Parcelamento!G12,Parcelamento!K12))
A10: Horas estimadas | B10: =Calculadora!B27 | D10: Parcela 3/4 | E10: =IF(E7="2 marcos","",IF(E7="3 marcos",Parcelamento!G13,Parcelamento!K13&" / "&TEXT(Parcelamento!K14,"R$ #,##0.00")))
A12: Resumo da demanda
A17: Solução sugerida
A22: Composição do investimento | D22: Observações comerciais
A23: Etapa | B23: Horas | C23: Subtotal | D23: Use este espaço para registrar premissas, limites de escopo, dependências ou ressalvas importantes antes de exportar.
A24: =Calculadora!A18 | B24: =Calculadora!B18 | C24: =Calculadora!D18
A25: =Calculadora!A19 | B25: =Calculadora!B19 | C25: =Calculadora!D19
A26: =Calculadora!A20 | B26: =Calculadora!B20 | C26: =Calculadora!D20
A27: =Calculadora!A21 | B27: =Calculadora!B21 | C27: =Calculadora!D21
A28: =Calculadora!A22 | B28: =Calculadora!B22 | C28: =Calculadora!D22
A29: =Calculadora!A23 | B29: =Calculadora!B23 | C29: =Calculadora!D23 | D29: Próximo passo sugerido
A30: =Calculadora!A24 | B30: =Calculadora!B24 | C30: =Calculadora!D24 | D30: Após validar este resumo, leve o cenário escolhido para a proposta comercial final.
A31: Total do cenário | B31: =Calculadora!B38
A35: Exportação | B35: Depois de revisar esta aba, exporte somente `Resumo-Proposta` em PDF pelo Excel para gerar um orçamento-resumo limpo.

Sheet Historico
A1: Histórico de Estimado, Vendido e Realizado
A2: Use esta aba após fechar a proposta e ao longo da execução do projeto para comparar horas planejadas, vendidas e reais.
A4: Projeto | B4: =Calculadora!B5 | D4: Cenário vendido | E4: =Calculadora!B14 | G4: Preço vendido | H4: =Calculadora!B38
A6: Etapa | B6: Horas estimadas | C6: Horas vendidas | D6: Horas reais | E6: Desvio vendido x estimado | F6: Desvio real x vendido | G6: Valor/h base | H6: Valor vendido da etapa | I6: Custo real pela etapa | J6: Saldo por etapa
A7: =Calculadora!A18 | B7: =Calculadora!B18 | C7: =B7 | D7: 0 | E7: =C7-B7 | F7: =D7-C7 | G7: =Calculadora!C18 | H7: =C7*G7 | I7: =D7*G7 | J7: =H7-I7
A8: =Calculadora!A19 | B8: =Calculadora!B19 | C8: =B8 | D8: 0 | E8: =C8-B8 | F8: =D8-C8 | G8: =Calculadora!C19 | H8: =C8*G8 | I8: =D8*G8 | J8: =H8-I8
A9: =Calculadora!A20 | B9: =Calculadora!B20 | C9: =B9 | D9: 0 | E9: =C9-B9 | F9: =D9-C9 | G9: =Calculadora!C20 | H9: =C9*G9 | I9: =D9*G9 | J9: =H9-I9
A10: =Calculadora!A21 | B10: =Calculadora!B21 | C10: =B10 | D10: 0 | E10: =C10-B10 | F10: =D10-C10 | G10: =Calculadora!C21 | H10: =C10*G10 | I10: =D10*G10 | J10: =H10-I10
A11: =Calculadora!A22 | B11: =Calculadora!B22 | C11: =B11 | D11: 0 | E11: =C11-B11 | F11: =D11-C11 | G11: =Calculadora!C22 | H11: =C11*G11 | I11: =D11*G11 | J11: =H11-I11
A12: =Calculadora!A23 | B12: =Calculadora!B23 | C12: =B12 | D12: 0 | E12: =C12-B12 | F12: =D12-C12 | G12: =Calculadora!C23 | H12: =C12*G12 | I12: =D12*G12 | J12: =H12-I12
A13: =Calculadora!A24 | B13: =Calculadora!B24 | C13: =B13 | D13: 0 | E13: =C13-B13 | F13: =D13-C13 | G13: =Calculadora!C24 | H13: =C13*G13 | I13: =D13*G13 | J13: =H13-I13
A16: Totais | B16: =SUM(B7:B13) | C16: =SUM(C7:C13) | D16: =SUM(D7:D13) | H16: =SUM(H7:H13) | I16: =SUM(I7:I13) | J16: =SUM(J7:J13)
A18: Leitura rápida | B18: Use `Horas vendidas` para refletir o que foi de fato combinado com o cliente. Use `Horas reais` ao longo da execução. O saldo por etapa ajuda a identificar onde o projeto ganhou ou perdeu margem operacional.

Sheet Parametros
A1: Parâmetros da Calculadora de Precificação
A2: Edite esta aba apenas quando as regras internas da RITO forem formalmente revisadas.
A4: Etapa | B4: Valor/hora base | D4: Complexidade | E4: Multiplicador | G4: Urgência | H4: Multiplicador | J4: Integrações | K4: Multiplicador | M4: Documentação extra | N4: Multiplicador | P4: Tipo de serviço | Q4: Faixa mínima | R4: Faixa máxima | T4: Pacote | U4: Multiplicador | V4: Descrição | X4: Cenário | Y4: Margem | Z4: Multiplicador | AA4: Uso sugerido | AC4: Modelo | AD4: Parcela 1 | AE4: Parcela 2 | AF4: Parcela 3 | AG4: Parcela 4
A5: Análise e descoberta | B5: 150 | D5: Baixa | E5: 0.95 | G5: Normal | H5: 1 | J5: Nenhuma | K5: 1 | M5: Não | N5: 1 | P5: Automação simples | Q5: 800 | R5: 2500 | T5: Essencial | U5: 0.92 | V5: Projetos enxutos, escopo mais direto e risco baixo. | X5: Mínimo defensável | Y5: 0.1 | Z5: 1 | AA5: Protege margem mínima sem subprecificar. | AC5: 2 marcos | AD5: 0.5 | AE5: 0.5 | AF5: 0 | AG5: 0
A6: Planejamento da solução | B6: 150 | D6: Média | E6: 1 | G6: Alta | H6: 1.1 | J6: Simples | K6: 1.08 | M6: Sim | N6: 1.05 | P6: Automação com integração | Q6: 1800 | R6: 4500 | T6: Operacional | U6: 1 | V6: Base padrão da RITO para propostas equilibradas. | X6: Ideal comercial | Y6: 0.15 | Z6: 1 | AA6: Referência principal para a maior parte das propostas. | AC6: 3 marcos | AD6: 0.4 | AE6: 0.3 | AF6: 0.3 | AG6: 0
A7: Desenvolvimento | B7: 180 | D7: Alta | E7: 1.15 | G7: Crítica | H7: 1.2 | J7: Múltiplas | K7: 1.15 | P7: Painel ou controle interno simples | Q7: 2500 | R7: 6000 | T7: Sob Medida | U7: 1.12 | V7: Projetos com maior personalização, criticidade ou responsabilidade. | X7: Premium estratégico | Y7: 0.22 | Z7: 1.06 | AA7: Aplicável quando há alto valor percebido, risco ou urgência relevante. | AC7: 4 marcos | AD7: 0.3 | AE7: 0.25 | AF7: 0.25 | AG7: 0.2
A8: Testes e ajustes | B8: 180 | P8: Ferramenta operacional pequena | Q8: 4500 | R8: 9000
A9: Entrega e orientação | B9: 150 | P9: Sistema sob medida de pequeno porte | Q9: 8000 | R9: 18000
A10: Suporte inicial | B10: 180 | P10: Projeto médio com integrações | Q10: 15000 | R10: 35000
A11: Treinamento adicional | B11: 150 | J11: Parâmetro global | K11: Valor | P11: Evolução ou manutenção técnica
J12: Margem padrão | K12: 0.15
J13: Entrada sugerida | K13: 0.4
J14: Parcela intermediária | K14: 0.3
J15: Saldo final | K15: 0.3
